odoo/addons/product_attribute_value_avoid_auto_fill/README.rst
odoo/addons/product_attribute_value_avoid_auto_fill/__init__.py
odoo/addons/product_attribute_value_avoid_auto_fill/__manifest__.py
odoo/addons/product_attribute_value_avoid_auto_fill/i18n/it.po
odoo/addons/product_attribute_value_avoid_auto_fill/i18n/product_attribute_value_avoid_auto_fill.pot
odoo/addons/product_attribute_value_avoid_auto_fill/models/__init__.py
odoo/addons/product_attribute_value_avoid_auto_fill/models/product_attribute.py
odoo/addons/product_attribute_value_avoid_auto_fill/models/product_template_attribute_line.py
odoo/addons/product_attribute_value_avoid_auto_fill/readme/CONTRIBUTORS.md
odoo/addons/product_attribute_value_avoid_auto_fill/readme/DESCRIPTION.md
odoo/addons/product_attribute_value_avoid_auto_fill/readme/USAGE.md
odoo/addons/product_attribute_value_avoid_auto_fill/static/description/icon.png
odoo/addons/product_attribute_value_avoid_auto_fill/static/description/index.html
odoo/addons/product_attribute_value_avoid_auto_fill/tests/__init__.py
odoo/addons/product_attribute_value_avoid_auto_fill/tests/test_product_attribute_value_avoid_auto_fill.py
odoo/addons/product_attribute_value_avoid_auto_fill/views/product_attribute_views.xml
odoo_addon_product_attribute_value_avoid_auto_fill-18.0.1.0.0.4.dist-info/METADATA
odoo_addon_product_attribute_value_avoid_auto_fill-18.0.1.0.0.4.dist-info/WHEEL
odoo_addon_product_attribute_value_avoid_auto_fill-18.0.1.0.0.4.dist-info/top_level.txt
odoo_addon_product_attribute_value_avoid_auto_fill-18.0.1.0.0.4.dist-info/RECORD
